MANIFEST.in
VERSION
setup.py
molano/__init__.py
molano/package.json
molano/runlevel.py
molano.egg-info/PKG-INFO
molano.egg-info/SOURCES.txt
molano.egg-info/dependency_links.txt
molano.egg-info/entry_points.txt
molano.egg-info/requires.txt
molano.egg-info/top_level.txt
molano/canon/__init__.py
molano/canon/billingdetails.py
molano/canon/commondeliverypoint.py
molano/canon/decimalmeid.py
molano/canon/device.py
molano/canon/devicetype.py
molano/canon/imei.py
molano/canon/ordertype.py
molano/canon/picqeruser.py
molano/canon/picqerwarehouse.py
molano/canon/productreference.py
molano/canon/purchasedproduct.py
molano/canon/purchaseorder.py
molano/canon/purchaser.py
molano/canon/serialnumber.py
molano/canon/shipment.py
molano/canon/shipmentitem.py
molano/canon/shippingdetails.py
molano/canon/supplier.py
molano/canon/udid.py
molano/canon/warehousereference.py
molano/canon/events/__init__.py
molano/canon/events/devicediscovered.py
molano/canon/events/ordercancelled.py
molano/canon/events/ordercompleted.py
molano/canon/events/orderplaced.py
molano/canon/events/phonecheckdeviceconnected.py
molano/canon/events/productsoutgoing.py
molano/canon/events/purchaseorderpurchased.py
molano/canon/events/stocklevelchanged.py
molano/infra/__init__.py
molano/infra/repo/__init__.py
molano/infra/repo/picqer.py
molano/lib/__init__.py
molano/lib/apiclient.py
molano/lib/google.py
molano/lib/serviceprincipal.py
molano/lib/servicerepository.py
molano/lib/serviceresource.py
molano/lib/credential/__init__.py
molano/lib/credential/icredential.py
molano/lib/credential/nullcredential.py
molano/lib/picqer/__init__.py
molano/lib/picqer/client.py
molano/lib/picqer/credential.py
molano/lib/picqer/supplier.py
molano/lib/picqer/user.py
molano/lib/picqer/warehouse.py
molano/runtime/ioc.py
molano/runtime/settings.py
molano/tests/test_integration_noop.py
molano/tests/test_system_noop.py
molano/tests/test_unit_noop.py