Metadata-Version: 2.1
Name: molano
Version: 0.29.0
Summary: Molano Common Library
Home-page: https://gitlab.com/unimatrixone
Author: Cochise Ruhulessin
Author-email: cochise.ruhulessin@unimatrixone.io
Classifier: Development Status :: 4 - Beta
Classifier: Environment :: Console
Classifier: Environment :: Web Environment
Classifier: Intended Audience :: Developers
Classifier: Intended Audience :: Financial and Insurance Industry
Classifier: Intended Audience :: Healthcare Industry
Classifier: License :: Other/Proprietary License
Classifier: Operating System :: POSIX
Classifier: Operating System :: POSIX :: Linux
Classifier: Programming Language :: Python :: 3.9
Classifier: Programming Language :: Python :: 3.10
Classifier: Programming Language :: Python :: 3 :: Only
Classifier: Topic :: Internet
Classifier: Topic :: Office/Business
Classifier: Topic :: Software Development :: Libraries
